rewarped/__init__.py
rewarped/autograd.py
rewarped/environment.py
rewarped/mpm_warp_env_mixin.py
rewarped/warp_env.py
rewarped/warp_utils.py
rewarped/assets/dflex/ant.xml
rewarped/assets/dflex/cartpole.urdf
rewarped/assets/dflex/half_cheetah.xml
rewarped/assets/dflex/hopper.xml
rewarped/assets/dflex/humanoid.xml
rewarped/assets/dflex/allegro_hand_description/allegro_hand_description_left.urdf
rewarped/assets/dflex/allegro_hand_description/allegro_hand_description_right.urdf
rewarped/assets/dflex/allegro_hand_description/meshes/base_link.STL
rewarped/assets/dflex/allegro_hand_description/meshes/base_link_left.STL
rewarped/assets/dflex/allegro_hand_description/meshes/link_0.STL
rewarped/assets/dflex/allegro_hand_description/meshes/link_1.STL
rewarped/assets/dflex/allegro_hand_description/meshes/link_12_left.STL
rewarped/assets/dflex/allegro_hand_description/meshes/link_12_right.STL
rewarped/assets/dflex/allegro_hand_description/meshes/link_13.STL
rewarped/assets/dflex/allegro_hand_description/meshes/link_14.STL
rewarped/assets/dflex/allegro_hand_description/meshes/link_15.STL
rewarped/assets/dflex/allegro_hand_description/meshes/link_15_tip.STL
rewarped/assets/dflex/allegro_hand_description/meshes/link_2.STL
rewarped/assets/dflex/allegro_hand_description/meshes/link_3.STL
rewarped/assets/dflex/allegro_hand_description/meshes/link_3_tip.STL
rewarped/assets/dflex/allegro_hand_description/meshes/link_4.STL
rewarped/assets/dflex/licenses/ant-LICENSE.txt
rewarped/assets/dflex/licenses/half-cheetah-LICENSE.txt
rewarped/assets/dflex/licenses/hopper-LICENSE.txt
rewarped/assets/dflex/licenses/humanoid-LICENSE.txt
rewarped/assets/dflex/licenses/snu-LICENSE.txt
rewarped/assets/dflex/usd/bear.usda
rewarped/assets/dflex/usd/ostrich.usda
rewarped/assets/dflex/usd/prop.usda
rewarped/assets/dflex/usd/table.usda
rewarped/assets/isaacgymenvs/urdf/objects/cube_multicolor.urdf
rewarped/assets/isaacgymenvs/urdf/objects/cube_multicolor_allegro.urdf
rewarped-1.3.3.dist-info/LICENSE
rewarped-1.3.3.dist-info/METADATA
rewarped-1.3.3.dist-info/WHEEL
rewarped-1.3.3.dist-info/top_level.txt
rewarped-1.3.3.dist-info/RECORD
