Metadata-Version: 2.2
Name: rewarped
Version: 1.3.3
Summary: A platform for reinforcement learning in differentiable multiphysics simulation
Author-email: rewarped contributors <etaoxing@users.noreply.github.com>
License: Apache License 2.0
Project-URL: GitHub, https://github.com/rewarped/rewarped
Classifier: Programming Language :: Python :: 3.10
Classifier: Programming Language :: Python :: 3.11
Classifier: Programming Language :: Python :: 3.12
Classifier: Programming Language :: Python :: 3.13
Classifier: Programming Language :: Python :: 3 :: Only
Classifier: License :: OSI Approved :: Apache Software License
Classifier: Operating System :: OS Independent
Requires-Python: >=3.10
License-File: LICENSE
Requires-Dist: warp-lang==1.3.3
Requires-Dist: usd-core==24.5
Requires-Dist: trimesh
Requires-Dist: pycollada
Provides-Extra: dev
Requires-Dist: ruff; extra == "dev"
